{
    "Time Series (Daily)": {
        "2024-11-19": {
            "4. close": "243.0900"
        },
        "2024-11-20": {
            "4. close": "240.7800"
        },
        "2024-11-21": {
            "4. close": "244.7600"
        },
        "2024-11-22": {
            "4. close": "248.5500"
        },
        "2024-11-25": {
            "4. close": "250.2900"
        },
        "2024-11-26": {
            "4. close": "249.9700"
        },
        "2024-11-27": {
            "4. close": "249.7900"
        },
        "2024-11-29": {
            "4. close": "249.7200"
        },
        "2024-12-02": {
            "4. close": "246.2500"
        },
        "2024-12-03": {
            "4. close": "244.8200"
        },
        "2024-12-04": {
            "4. close": "243.4000"
        },
        "2024-12-05": {
            "4. close": "245.4800"
        },
        "2024-12-06": {
            "4. close": "247.3600"
        },
        "2024-12-09": {
            "4. close": "243.8100"
        },
        "2024-12-10": {
            "4. close": "242.8600"
        },
        "2024-12-11": {
            "4. close": "243.5300"
        },
        "2024-12-12": {
            "4. close": "241.5300"
        },
        "2024-12-13": {
            "4. close": "239.9400"
        },
        "2024-12-16": {
            "4. close": "239.5800"
        },
        "2024-12-17": {
            "4. close": "238.3600"
        },
        "2024-12-18": {
            "4. close": "230.3700"
        },
        "2024-12-19": {
            "4. close": "232.9600"
        },
        "2024-12-20": {
            "4. close": "237.6000"
        },
        "2024-12-23": {
            "4. close": "238.3900"
        },
        "2024-12-24": {
            "4. close": "242.3100"
        },
        "2024-12-26": {
            "4. close": "243.1400"
        },
        "2024-12-27": {
            "4. close": "241.1700"
        },
        "2024-12-30": {
            "4. close": "239.3200"
        },
        "2024-12-31": {
            "4. close": "239.7100"
        },
        "2025-01-02": {
            "4. close": "240.0000"
        },
        "2025-01-03": {
            "4. close": "243.2800"
        },
        "2025-01-06": {
            "4. close": "240.8500"
        },
        "2025-01-07": {
            "4. close": "243.1700"
        },
        "2025-01-08": {
            "4. close": "243.1300"
        },
        "2025-01-10": {
            "4. close": "239.8700"
        },
        "2025-01-13": {
            "4. close": "244.2100"
        },
        "2025-01-14": {
            "4. close": "247.4700"
        },
        "2025-01-15": {
            "4. close": "252.3500"
        },
        "2025-01-16": {
            "4. close": "254.2700"
        },
        "2025-01-17": {
            "4. close": "259.1600"
        },
        "2025-01-21": {
            "4. close": "263.0300"
        },
        "2025-01-22": {
            "4. close": "262.8400"
        },
        "2025-01-23": {
            "4. close": "265.9500"
        },
        "2025-01-24": {
            "4. close": "264.8400"
        },
        "2025-01-27": {
            "4. close": "265.8500"
        },
        "2025-01-28": {
            "4. close": "267.1400"
        },
        "2025-01-29": {
            "4. close": "266.5800"
        },
        "2025-01-30": {
            "4. close": "268.2300"
        },
        "2025-01-31": {
            "4. close": "267.3000"
        },
        "2025-02-03": {
            "4. close": "266.8100"
        },
        "2025-02-04": {
            "4. close": "267.9400"
        },
        "2025-02-05": {
            "4. close": "270.4300"
        },
        "2025-02-06": {
            "4. close": "276.9000"
        },
        "2025-02-07": {
            "4. close": "275.8000"
        },
        "2025-02-10": {
            "4. close": "271.0400"
        },
        "2025-02-11": {
            "4. close": "274.9900"
        },
        "2025-02-12": {
            "4. close": "275.4500"
        },
        "2025-02-13": {
            "4. close": "276.3200"
        },
        "2025-02-14": {
            "4. close": "276.5900"
        },
        "2025-02-18": {
            "4. close": "279.9500"
        },
        "2025-02-19": {
            "4. close": "279.2500"
        },
        "2025-02-20": {
            "4. close": "266.8000"
        },
        "2025-02-21": {
            "4. close": "264.2400"
        },
        "2025-02-24": {
            "4. close": "261.3400"
        },
        "2025-02-25": {
            "4. close": "257.4000"
        },
        "2025-02-26": {
            "4. close": "258.7900"
        },
        "2025-02-27": {
            "4. close": "259.0500"
        },
        "2025-02-28": {
            "4. close": "264.6500"
        },
        "2025-03-03": {
            "4. close": "260.6200"
        },
        "2025-03-04": {
            "4. close": "250.2500"
        },
        "2025-03-05": {
            "4. close": "251.5300"
        },
        "2025-03-06": {
            "4. close": "246.5400"
        },
        "2025-03-07": {
            "4. close": "242.2800"
        },
        "2025-03-10": {
            "4. close": "232.2200"
        },
        "2025-03-11": {
            "4. close": "229.1400"
        },
        "2025-03-12": {
            "4. close": "227.9000"
        },
        "2025-03-13": {
            "4. close": "225.1900"
        },
        "2025-03-14": {
            "4. close": "232.4400"
        },
        "2025-03-17": {
            "4. close": "233.9300"
        },
        "2025-03-18": {
            "4. close": "234.9700"
        },
        "2025-03-19": {
            "4. close": "239.1100"
        },
        "2025-03-20": {
            "4. close": "239.0100"
        },
        "2025-03-21": {
            "4. close": "241.6300"
        },
        "2025-03-24": {
            "4. close": "248.0600"
        },
        "2025-03-25": {
            "4. close": "251.1300"
        },
        "2025-03-26": {
            "4. close": "251.0300"
        },
        "2025-03-27": {
            "4. close": "248.1200"
        },
        "2025-03-28": {
            "4. close": "242.8500"
        },
        "2025-03-31": {
            "4. close": "245.3000"
        },
        "2025-04-01": {
            "4. close": "243.6600"
        },
        "2025-04-02": {
            "4. close": "245.8200"
        },
        "2025-04-03": {
            "4. close": "228.6900"
        },
        "2025-04-04": {
            "4. close": "210.2800"
        },
        "2025-04-07": {
            "4. close": "214.4400"
        },
        "2025-04-08": {
            "4. close": "216.8700"
        },
        "2025-04-09": {
            "4. close": "234.3400"
        },
        "2025-04-10": {
            "4. close": "227.1100"
        },
        "2025-04-11": {
            "4. close": "236.2000"
        },
        "2025-04-14": {
            "4. close": "234.7200"
        },
        "2025-04-15": {
            "4. close": "233.1300"
        },
        "2025-04-16": {
            "4. close": "229.6100"
        },
        "2025-04-17": {
            "4. close": "231.9600"
        },
        "2025-04-18": {
            "4. close": "235.6574"
        },
        "2025-04-19": {
            "4. close": "236.0510"
        },
        "2025-04-20": {
            "4. close": "236.5103"
        },
        "2025-04-21": {
            "4. close": "236.9873"
        },
        "2025-04-22": {
            "4. close": "237.4524"
        },
        "2025-04-23": {
            "4. close": "237.8894"
        },
        "2025-04-24": {
            "4. close": "238.2912"
        }
    }
}